ebaycrawler/__init__.py
ebaycrawler/exceptions.py
ebaycrawler/logger.py
ebaycrawler/logo.ansi
ebaycrawler/main.py
ebaycrawler/fileio/__init__.py
ebaycrawler/fileio/writers.py
ebaycrawler/parsing/__init__.py
ebaycrawler/parsing/parsers.py
ebaycrawler/parsing/requesters.py
ebaycrawler-0.1.15.dist-info/LICENSE
ebaycrawler-0.1.15.dist-info/METADATA
ebaycrawler-0.1.15.dist-info/WHEEL
ebaycrawler-0.1.15.dist-info/entry_points.txt
ebaycrawler-0.1.15.dist-info/top_level.txt
ebaycrawler-0.1.15.dist-info/RECORD
