Metadata-Version: 2.1
Name: ebaycrawler
Version: 0.1.15
Home-page: https://github.com/ov3rwrite/ebaycrawler
Author: ov3rwrite
Author-email: ilyabelykh123@gmail.com
License: MIT
License-File: LICENSE
Requires-Dist: bs4 (~=0.0.1)
Requires-Dist: asyncio (~=3.4.3)
Requires-Dist: aiohttp (~=3.7.4.post0)
Requires-Dist: requests (~=2.26.0)
Requires-Dist: pandas (~=1.3.4)
Requires-Dist: openpyxl (~=3.0.10)
